TensorMap/__init__.py
TensorMap-0.0.1.dist-info/LICENSE
TensorMap-0.0.1.dist-info/METADATA
TensorMap-0.0.1.dist-info/WHEEL
TensorMap-0.0.1.dist-info/top_level.txt
TensorMap-0.0.1.dist-info/RECORD
