Metadata-Version: 2.1
Name: TensorMap
Version: 0.0.1
Summary: Data Visualizer
Home-page: https://github.com/social-learning/TensorMap
Author: social-learning
Author-email: byfan@wisc.edu
License: UNKNOWN
Platform: UNKNOWN
Classifier: Programming Language :: Python :: 3
Classifier: License :: OSI Approved :: MIT License
Classifier: Operating System :: OS Independent
Requires-Python: >=3.6
